topotoolbox-0.0.7.dist-info/WHEEL
topotoolbox-0.0.7.dist-info/METADATA
topotoolbox-0.0.7.dist-info/RECORD
topotoolbox-0.0.7.dist-info/licenses/LICENSE
topotoolbox-0.0.7.dist-info/licenses/LICENSES_bundled
topotoolbox.libs/libgomp-24e2ab19.so.1.0.0
topotoolbox/graphflood_object.py
topotoolbox/flow_object.py
topotoolbox/_flow.cpython-311-x86_64-linux-gnu.so
topotoolbox/utils.py
topotoolbox/stream_object.py
topotoolbox/_grid.cpython-311-x86_64-linux-gnu.so
topotoolbox/graphflood.py
topotoolbox/grid_object.py
topotoolbox/stream_functions.py
topotoolbox/interface.py
topotoolbox/_morphology.cpython-311-x86_64-linux-gnu.so
topotoolbox/_stream.cpython-311-x86_64-linux-gnu.so
topotoolbox/_graphflood.cpython-311-x86_64-linux-gnu.so
topotoolbox/__init__.py
