Metadata-Version: 2.2
Name: topotoolbox
Version: 0.0.7
Summary: Python interface to TopoToolbox.
Keywords: TopoToolbox
Author-Email: Wolfgang Schwanghart <w.schwanghart@geo.uni-potsdam.de>, Dirk Scherler <scherler@fz-potsdam.de>, Will Kearney <william.kearney@uni-potsdam.de>, Theo Bringezu <theophil.bringezu@uni-potsdam.de>
License:                     GNU GENERAL PUBLIC LICENSE
Project-URL: Homepage, https://topotoolbox.github.io
Project-URL: Repository, https://github.com/TopoToolbox/pytopotoolbox
Project-URL: Issues, https://github.com/TopoToolbox/pytopotoolbox/issues
Requires-Python: >=3.10
Requires-Dist: numpy>=1.23.5
Requires-Dist: matplotlib
Requires-Dist: scipy
Requires-Dist: rasterio
Requires-Dist: geopandas
Requires-Dist: shapely
Requires-Dist: clarabel
Provides-Extra: opensimplex
Requires-Dist: opensimplex; extra == "opensimplex"
Provides-Extra: test
Requires-Dist: pytest; extra == "test"
Requires-Dist: opensimplex; extra == "test"
